NISP/__init__.py
NISP/NISP/Cluster.py
NISP/NISP/Counter.py
NISP/NISP/Create_submitSL_slurm_Main.py
NISP/NISP/Interpolation_Connection.py
NISP/NISP/Interpolation_rules.py
NISP/NISP/Manual_Mode.py
NISP/NISP/Run_Interpolation_Scheme.py
NISP/NISP/get_interpolation_data_from_ase_calculator.py
NISP/NISP/get_interpolation_data_from_ase_from_file.py
NISP/NISP/input_from_procesed_VASP_files.py
NISP/NISP/motif_methods.py
NISP/Subsidiary_Programs/Place_VASP_Files_into_folders.py
NISP/Subsidiary_Programs/Run_submitSL_slurm.py
NISP-1.3.5.data/scripts/Place_VASP_Files_into_folders.py
NISP-1.3.5.data/scripts/Run_submitSL_slurm.py
NISP-1.3.5.dist-info/LICENSE
NISP-1.3.5.dist-info/METADATA
NISP-1.3.5.dist-info/WHEEL
NISP-1.3.5.dist-info/top_level.txt
NISP-1.3.5.dist-info/RECORD
