Metadata-Version: 2.1
Name: NISP
Version: 1.3.5
Summary: The Nanocluster Interpolation Scheme Program (NISP) is designed to perform an interpolation scheme that gives idea of the types of perfect, closed-shell and open-shell clusters for a cluster at selected sizes.
Home-page: https://blogs.otago.ac.nz/annagarden/
Author: Geoffrey R. Weal, Dr. Anna L. Garden, Dr. Andreas Pedersen and Prof. Hannes Jónsson
Author-email: anna.garden@otago.ac.nz
License: GNU AFFERO GENERAL PUBLIC LICENSE
Download-URL: https://github.com/GardenGroupUO/NIS/archive/v1.3.5.tar.gz
Keywords: nanoclusters,nanoparticles,clusters
Platform: UNKNOWN
Classifier: Development Status :: 3 - Alpha
Classifier: Intended Audience :: Science/Research
Classifier: Natural Language :: English
Classifier: Operating System :: MacOS :: MacOS X
Classifier: Operating System :: POSIX :: Linux
Classifier: Operating System :: Unix
Classifier: Topic :: Scientific/Engineering :: Chemistry
Classifier: Topic :: Scientific/Engineering :: Physics
Classifier: Topic :: Scientific/Engineering :: Mathematics
Classifier: Topic :: Scientific/Engineering :: Artificial Intelligence
Classifier: Natural Language :: English
Classifier: License :: OSI Approved :: GNU Affero General Public License v3
Classifier: Programming Language :: Python :: 3 :: Only
Classifier: Programming Language :: Python :: 3.6
Classifier: Programming Language :: Python :: 3.7
Classifier: Programming Language :: Python :: 3.8
Classifier: Programming Language :: Python :: 3.9
Requires-Dist: numpy
Requires-Dist: scipy
Requires-Dist: matplotlib
Requires-Dist: ase (>=3.21.1)
Requires-Dist: Sphinx
Requires-Dist: sphinx-rtd-theme
Requires-Dist: sphinx-tabs
Requires-Dist: sphinxcontrib-applehelp
Requires-Dist: sphinxcontrib-devhelp
Requires-Dist: sphinxcontrib-htmlhelp
Requires-Dist: sphinxcontrib-jsmath
Requires-Dist: sphinxcontrib-plantuml
Requires-Dist: sphinxcontrib-qthelp
Requires-Dist: sphinxcontrib-serializinghtml
Requires-Dist: sphinxcontrib-wiki
